{"nodes": [{"id": "users_ranveeraiden_library_cloudstorage_onedrive_eroad_desktop_workspace_iwiki_ingestion_service_app_db_models_py", "label": "models.py", "file_type": "code", "source_file": "ingestion-service/app/db/models.py", "source_location": "L1"}, {"id": "db_models_base", "label": "Base", "file_type": "code", "source_file": "ingestion-service/app/db/models.py", "source_location": "L10"}, {"id": "declarativebase", "label": "DeclarativeBase", "file_type": "code", "source_file": "", "source_location": ""}, {"id": "db_models_document", "label": "Document", "file_type": "code", "source_file": "ingestion-service/app/db/models.py", "source_location": "L14"}, {"id": "db_models_syncstate", "label": "SyncState", "file_type": "code", "source_file": "ingestion-service/app/db/models.py", "source_location": "L37"}, {"id": "db_models_productexpert", "label": "ProductExpert", "file_type": "code", "source_file": "ingestion-service/app/db/models.py", "source_location": "L46"}, {"id": "db_models_rationale_47", "label": "Synthesised product/component knowledge used by AI agents and query service.", "file_type": "rationale", "source_file": "ingestion-service/app/db/models.py", "source_location": "L47"}], "edges": [{"source": "users_ranveeraiden_library_cloudstorage_onedrive_eroad_desktop_workspace_iwiki_ingestion_service_app_db_models_py", "target": "uuid", "relation": "imports", "context": "import", "confidence": "EXTRACTED", "source_file": "ingestion-service/app/db/models.py", "source_location": "L1", "weight": 1.0}, {"source": "users_ranveeraiden_library_cloudstorage_onedrive_eroad_desktop_workspace_iwiki_ingestion_service_app_db_models_py", "target": "datetime", "relation": "imports_from", "context": "import", "confidence": "EXTRACTED", "source_file": "ingestion-service/app/db/models.py", "source_location": "L2", "weight": 1.0}, {"source": "users_ranveeraiden_library_cloudstorage_onedrive_eroad_desktop_workspace_iwiki_ingestion_service_app_db_models_py", "target": "typing", "relation": "imports_from", "context": "import", "confidence": "EXTRACTED", "source_file": "ingestion-service/app/db/models.py", "source_location": "L3", "weight": 1.0}, {"source": "users_ranveeraiden_library_cloudstorage_onedrive_eroad_desktop_workspace_iwiki_ingestion_service_app_db_models_py", "target": "sqlalchemy", "relation": "imports_from", "context": "import", "confidence": "EXTRACTED", "source_file": "ingestion-service/app/db/models.py", "source_location": "L5", "weight": 1.0}, {"source": "users_ranveeraiden_library_cloudstorage_onedrive_eroad_desktop_workspace_iwiki_ingestion_service_app_db_models_py", "target": "sqlalchemy_dialects_postgresql", "relation": "imports_from", "context": "import", "confidence": "EXTRACTED", "source_file": "ingestion-service/app/db/models.py", "source_location": "L6", "weight": 1.0}, {"source": "users_ranveeraiden_library_cloudstorage_onedrive_eroad_desktop_workspace_iwiki_ingestion_service_app_db_models_py", "target": "sqlalchemy_orm", "relation": "imports_from", "context": "import", "confidence": "EXTRACTED", "source_file": "ingestion-service/app/db/models.py", "source_location": "L7", "weight": 1.0}, {"source": "users_ranveeraiden_library_cloudstorage_onedrive_eroad_desktop_workspace_iwiki_ingestion_service_app_db_models_py", "target": "db_models_base", "relation": "contains", "confidence": "EXTRACTED", "source_file": "ingestion-service/app/db/models.py", "source_location": "L10", "weight": 1.0}, {"source": "db_models_base", "target": "declarativebase", "relation": "inherits", "confidence": "EXTRACTED", "source_file": "ingestion-service/app/db/models.py", "source_location": "L10", "weight": 1.0}, {"source": "users_ranveeraiden_library_cloudstorage_onedrive_eroad_desktop_workspace_iwiki_ingestion_service_app_db_models_py", "target": "db_models_document", "relation": "contains", "confidence": "EXTRACTED", "source_file": "ingestion-service/app/db/models.py", "source_location": "L14", "weight": 1.0}, {"source": "db_models_document", "target": "db_models_base", "relation": "inherits", "confidence": "EXTRACTED", "source_file": "ingestion-service/app/db/models.py", "source_location": "L14", "weight": 1.0}, {"source": "users_ranveeraiden_library_cloudstorage_onedrive_eroad_desktop_workspace_iwiki_ingestion_service_app_db_models_py", "target": "db_models_syncstate", "relation": "contains", "confidence": "EXTRACTED", "source_file": "ingestion-service/app/db/models.py", "source_location": "L37", "weight": 1.0}, {"source": "db_models_syncstate", "target": "db_models_base", "relation": "inherits", "confidence": "EXTRACTED", "source_file": "ingestion-service/app/db/models.py", "source_location": "L37", "weight": 1.0}, {"source": "users_ranveeraiden_library_cloudstorage_onedrive_eroad_desktop_workspace_iwiki_ingestion_service_app_db_models_py", "target": "db_models_productexpert", "relation": "contains", "confidence": "EXTRACTED", "source_file": "ingestion-service/app/db/models.py", "source_location": "L46", "weight": 1.0}, {"source": "db_models_productexpert", "target": "db_models_base", "relation": "inherits", "confidence": "EXTRACTED", "source_file": "ingestion-service/app/db/models.py", "source_location": "L46", "weight": 1.0}, {"source": "db_models_rationale_47", "target": "db_models_productexpert", "relation": "rationale_for", "confidence": "EXTRACTED", "source_file": "ingestion-service/app/db/models.py", "source_location": "L47", "weight": 1.0}], "raw_calls": []}